README.md
setup.cfg
setup.py
onshapepy/__init__.py
onshapepy/assembly.py
onshapepy/document.py
onshapepy/part.py
onshapepy/play.py
onshapepy/uri.py
onshapepy.egg-info/PKG-INFO
onshapepy.egg-info/SOURCES.txt
onshapepy.egg-info/dependency_links.txt
onshapepy.egg-info/requires.txt
onshapepy.egg-info/top_level.txt
onshapepy/core/__init__.py
onshapepy/core/client.py
onshapepy/core/context.py
onshapepy/core/onshape.py
onshapepy/core/units.py
onshapepy/core/utils.py
tests/__init__.py
tests/conftest.py
tests/test_assembly.py
tests/test_context.py
tests/test_core.py
tests/test_document.py
tests/test_part.py
tests/test_uri.py