Metadata-Version: 1.0
Name: onshapepy
Version: 0.0.17
Summary: Drive part configurations from Python.
Home-page: https://aguaclara.github.io/onshapepy/
Author: Ethan Keller
Author-email: UNKNOWN
License: The MIT License (MIT)
Platform: UNKNOWN
